{
  "$schema": "https://ui.shadcn.com/schema/registry-item.json",
  "name": "movie-pass",
  "type": "registry:ui",
  "title": "MoviePassButton",
  "description": "A ticket-style button with a tear-off animation, like a cinema stub.",
  "files": [
    {
      "path": "components/evil-buttons/movie-pass.tsx",
      "type": "registry:ui",
      "target": "components/evil-buttons/movie-pass.tsx",
      "content": "\"use client\";\r\n\r\nimport { ReactNode, useState } from \"react\";\r\nimport { motion, AnimatePresence } from \"motion/react\";\r\nimport { cn } from \"@/lib/utils\";\r\n\r\nconst colorMap = {\r\n  primary: \"bg-primary\",\r\n  secondary: \"bg-secondary\",\r\n  destructive: \"bg-destructive\",\r\n  accent: \"bg-accent\",\r\n} as const;\r\n\r\ntype Color = keyof typeof colorMap;\r\n\r\nconst textMap: Record<Color, string> = {\r\n  primary: \"text-primary-foreground\",\r\n  secondary: \"text-secondary-foreground\",\r\n  destructive: \"text-destructive-foreground\",\r\n  accent: \"text-accent-foreground\",\r\n};\r\n\r\nfunction MoviePassButton({\r\n  children,\r\n  className,\r\n  color = \"primary\",\r\n  icon,\r\n  onClick,\r\n}: {\r\n  children: ReactNode;\r\n  className?: string;\r\n  color?: Color;\r\n  icon?: ReactNode;\r\n  onClick?: () => void;\r\n}) {\r\n  const [torn, setTorn] = useState(false);\r\n  const [animating, setAnimating] = useState(false);\r\n\r\n  const bg = colorMap[color];\r\n  const text = textMap[color];\r\n\r\n  const handleClick = () => {\r\n    if (animating) return;\r\n    setAnimating(true);\r\n    setTorn(true);\r\n\r\n    setTimeout(() => {\r\n      setTorn(false);\r\n      setAnimating(false);\r\n      onClick?.();\r\n    }, 750);\r\n  };\r\n\r\n  const labelContent = (\r\n    <>\r\n      <div className=\"absolute left-0 top-0 w-3 h-3 rounded-full bg-background -translate-x-1/2 -translate-y-1/2\" />\r\n      <div className=\"absolute left-0 bottom-0 w-3 h-3 rounded-full bg-background -translate-x-1/2 translate-y-1/2\" />\r\n      <span\r\n        className={cn(\r\n          \"relative z-10 font-bold text-sm tracking-wide select-none whitespace-nowrap\",\r\n          text,\r\n        )}\r\n      >\r\n        {children}\r\n      </span>\r\n    </>\r\n  );\r\n\r\n  return (\r\n    <div\r\n      className={cn(\r\n        \"relative inline-flex items-center\",\r\n        \"[filter:drop-shadow(0_3px_0px_hsl(var(--foreground)/0.2))]\",\r\n        \"hover:[filter:drop-shadow(0_5px_0px_hsl(var(--foreground)/0.25))]\",\r\n        className,\r\n      )}\r\n    >\r\n      {/* Left cap — never moves */}\r\n      <button\r\n        onClick={handleClick}\r\n        className={cn(\r\n          \"relative z-10 w-11 h-11 flex items-center justify-center flex-shrink-0 rounded-l-xl cursor-pointer border-none\",\r\n          bg,\r\n        )}\r\n        style={{ WebkitTapHighlightColor: \"transparent\" }}\r\n      >\r\n        <div className=\"absolute inset-[6px_4px_6px_8px] bg-white/20 rounded-l-md pointer-events-none\" />\r\n        {icon && (\r\n          <span className={cn(\"relative z-10 text-lg leading-none\", text)}>\r\n            {icon}\r\n          </span>\r\n        )}\r\n      </button>\r\n\r\n      {/* Wrapper — always holds space via the invisible ghost label */}\r\n      <div className=\"relative h-11\">\r\n        {/* Ghost — invisible but always in flow, permanently holds the width */}\r\n        <div\r\n          aria-hidden\r\n          className={cn(\r\n            \"invisible flex items-center pl-2.5 pr-5 h-full\",\r\n            \"border-l-2 border-dashed border-transparent\",\r\n          )}\r\n        >\r\n          <span className=\"font-bold text-sm tracking-wide whitespace-nowrap\">\r\n            {children}\r\n          </span>\r\n        </div>\r\n\r\n        {/* Animated label — absolute on top of the ghost */}\r\n        <AnimatePresence>\r\n          {!torn && (\r\n            <motion.div\r\n              key=\"attached\"\r\n              exit={{ y: 80, rotate: 20, opacity: 0 }}\r\n              transition={{ duration: 0.55, ease: [0.4, 0, 1, 1] }}\r\n              onClick={handleClick}\r\n              className={cn(\r\n                \"absolute inset-0 flex items-center pl-2.5 pr-5 rounded-r-xl cursor-pointer\",\r\n                \"border-l-2 border-dashed border-white/30\",\r\n                bg,\r\n              )}\r\n            >\r\n              {labelContent}\r\n            </motion.div>\r\n          )}\r\n        </AnimatePresence>\r\n      </div>\r\n    </div>\r\n  );\r\n}\r\n\r\nexport default MoviePassButton;\r\n"
    }
  ],
  "dependencies": [
    "motion",
    "clsx",
    "tailwind-merge"
  ]
}
